__init__.py
wrapica/__init__.py
wrapica/bundle/__init__.py
wrapica/bundle/functions/__init__.py
wrapica/bundle/functions/bundle_functions.py
wrapica/data/__init__.py
wrapica/data/functions/__init__.py
wrapica/data/functions/data_functions.py
wrapica/enums/__init__.py
wrapica/job/__init__.py
wrapica/job/functions/__init__.py
wrapica/job/functions/job_functions.py
wrapica/libica_exceptions/__init__.py
wrapica/libica_models/__init__.py
wrapica/literals/__init__.py
wrapica/pipelines/__init__.py
wrapica/pipelines/functions/__init__.py
wrapica/pipelines/functions/pipelines_functions.py
wrapica/project/__init__.py
wrapica/project/functions/project_functions.py
wrapica/project_analysis/__init__.py
wrapica/project_analysis/functions/__init__.py
wrapica/project_analysis/functions/project_analysis_functions.py
wrapica/project_data/__init__.py
wrapica/project_data/functions/__init__.py
wrapica/project_data/functions/project_data_functions.py
wrapica/project_pipelines/__init__.py
wrapica/project_pipelines/classes/__init__.py
wrapica/project_pipelines/classes/analysis.py
wrapica/project_pipelines/classes/cwl_analysis.py
wrapica/project_pipelines/classes/nextflow_analysis.py
wrapica/project_pipelines/functions/__init__.py
wrapica/project_pipelines/functions/project_pipelines_functions.py
wrapica/region/__init__.py
wrapica/region/functions/__init__.py
wrapica/region/functions/region_functions.py
wrapica/storage_configuration/__init__.py
wrapica/storage_configuration/functions/__init__.py
wrapica/storage_configuration/functions/storage_configuration_functions.py
wrapica/storage_credentials/__init__.py
wrapica/storage_credentials/functions/__init__.py
wrapica/storage_credentials/functions/storage_credentials_functions.py
wrapica/tenant/__init__.py
wrapica/tenant/functions/__init__.py
wrapica/tenant/functions/tenant_functions.py
wrapica/user/__init__.py
wrapica/user/functions/__init__.py
wrapica/user/functions/user_functions.py
wrapica/utils/__init__.py
wrapica/utils/configuration.py
wrapica-2.40.1.post20251107162736.dist-info/licenses/LICENSE
wrapica-2.40.1.post20251107162736.dist-info/METADATA
wrapica-2.40.1.post20251107162736.dist-info/WHEEL
wrapica-2.40.1.post20251107162736.dist-info/top_level.txt
wrapica-2.40.1.post20251107162736.dist-info/RECORD
